jinja_unquote_resolvers_filter/__init__.py
jinja_unquote_resolvers_filter/unquote_resolvers.py
jinja_unquote_resolvers_filter-1.1.0.dist-info/METADATA
jinja_unquote_resolvers_filter-1.1.0.dist-info/WHEEL
jinja_unquote_resolvers_filter-1.1.0.dist-info/RECORD
