Metadata-Version: 2.1
Name: jinja-unquote-resolvers-filter
Version: 1.1.0
Summary: A Jinja filter for allowing Sceptre resolvers in var files
Home-page: https://github.com/Sceptre/jinja-unquote-resolvers-filter
License: Apache-2.0
Keywords: sceptre,jinja
Author: Sceptre
Author-email: sceptreorg@gmail.com
Requires-Python: >=3.8,<4.0
Classifier: Environment :: Console
Classifier: Intended Audience :: Developers
Classifier: License :: OSI Approved :: Apache Software License
Classifier: Natural Language :: English
Classifier: Programming Language :: Python :: 3
Classifier: Programming Language :: Python :: 3.8
Classifier: Programming Language :: Python :: 3.9
Classifier: Programming Language :: Python :: 3.10
Classifier: Programming Language :: Python :: 3.11
Classifier: Programming Language :: Python :: 3.12
Requires-Dist: Jinja2 (>=3.1.2,<4.0.0)
Requires-Dist: pyyaml (>=6.0,<7.0)
Project-URL: Repository, https://github.com/Sceptre/jinja-unquote-resolvers-filter
